exgrads/-vectorize.py
exgrads/__init__.py
exgrads/grad1.py
exgrads/hooks.py
exgrads/trH.py
ExGrads-0.1.12.dist-info/METADATA
ExGrads-0.1.12.dist-info/WHEEL
ExGrads-0.1.12.dist-info/top_level.txt
ExGrads-0.1.12.dist-info/RECORD
