Metadata-Version: 2.1
Name: ExGrads
Version: 0.1.12
Summary: calculate example-wise gradient
Home-page: https://gitlab.com/takuo-h/examplewise-gradients
Author: Takuo Hamaguchi
Author-email: nyahha@gmail.com
License: MIT
Platform: UNKNOWN
Classifier: License :: OSI Approved :: MIT License
Classifier: Programming Language :: Python :: 3.6
Requires-Dist: torch
